{
    "rating": {
        "max": 10,
        "numRaters": 9270,
        "average": "8.1",
        "min": 0
    },
    "subtitle": "",
    "author": [
        "老舍"
    ],
    "pubdate": "1962-10",
    "tags": [
        {
            "count": 1415,
            "name": "老舍",
            "title": "老舍"
        },
        {
            "count": 879,
            "name": "中国文学",
            "title": "中国文学"
        },
        {
            "count": 779,
            "name": "小说",
            "title": "小说"
        },
        {
            "count": 410,
            "name": "骆驼祥子",
            "title": "骆驼祥子"
        },
        {
            "count": 336,
            "name": "中国",
            "title": "中国"
        },
        {
            "count": 329,
            "name": "名著",
            "title": "名著"
        },
        {
            "count": 318,
            "name": "经典",
            "title": "经典"
        },
        {
            "count": 247,
            "name": "文学",
            "title": "文学"
        }
    ],
    "origin_title": "",
    "image": "https://img1.doubanio.com/view/subject/m/public/s9140520.jpg",
    "binding": "平装",
    "translator": [],
    "catalog": "\n      ",
    "pages": "224",
    "images": {
        "small": "https://img1.doubanio.com/view/subject/s/public/s9140520.jpg",
        "large": "https://img1.doubanio.com/view/subject/l/public/s9140520.jpg",
        "medium": "https://img1.doubanio.com/view/subject/m/public/s9140520.jpg"
    },
    "alt": "https://book.douban.com/subject/1028693/",
    "id": "1028693",
    "publisher": "人民文学出版社",
    "isbn10": "7020031897",
    "isbn13": "9787020031894",
    "title": "骆驼祥子",
    "url": "https://api.douban.com/v2/book/1028693",
    "alt_title": "",
    "author_intro": "老舍（1899-1966），原名舒庆春，字舍予，北京人。自幼丧父，家境贫寒，身受旧北京下层平民社会生活及思想观念、审美情趣的影响。1924年赴英国任教，并开始文学创作，以幽默风格引人关注。1930年回国后创作了《骆驼祥子》、《离婚》、《牛天赐传》、《月牙儿》等作品，确立了现代文学史上都市平民文学大家的地位。抗战期间主持中华全国文艺界抗敌协会工作，并写下了百万字长篇小说《四世同堂》。1949年后，又有《龙须沟》、《茶馆》等话剧力作问世，获“人民艺术家”的称号。",
    "summary": "老舍笔下的祥子来自乡间，带着中国农村破败凋敝的大背景，也带着农民的质朴和固执。当他认准了拉车这一行，他就成了“车迷”，一心想买上自己的车。凭着勤劳和坚韧，他用三年的时间省吃俭用，终于实现了这个理想，成为自食其力的上等车夫。但当时中国军阀混战的社会环境，不容他有丝毫的个人幻想，不到半年，他就在兵荒马乱中被逃兵掳走，失去了洋车，只牵回三匹骆驼。祥子没有灰心，他依然倔强地从头开始，更加克己地拉车攒钱。可这次还没有等他再买上车，所有的积蓄又被侦探敲诈洗劫一空，买车的梦想再次成为泡影。当他又一次拉上自己的车，是以与虎妞成就畸形的婚姻为代价的。但好景不长，虎妞死于难产，祥子人车两空。生活捉弄了他，他也开始游戏生活，吃喝嫖赌，出卖他人换钱，祥子彻底堕落为城市的垃圾，变成一具失去灵魂的行尸走肉。老舍通过这个人物写出了不合理的社会制度对下层劳动者生活空间的威压。作品中另一个鲜活的人物是虎妞。她身上十足的生活味道，她的可鄙也可悲的命运给人以深刻的印象。老舍将中国传统的叙事方法融入外国文学的景物铺排和心理描写，使祥子和虎妞成为家喻户晓、耳熟能详的人物形象。",
    "series": {
        "id": "4492",
        "title": "中学生课外文学名著必读"
    },
    "price": "9.80元"
}