{
    "rating": {
        "max": 10,
        "numRaters": 14501,
        "average": "7.5",
        "min": 0
    },
    "subtitle": "",
    "author": [
        "（香港）亦舒"
    ],
    "pubdate": "1996年9月",
    "tags": [
        {
            "count": 4747,
            "name": "亦舒",
            "title": "亦舒"
        },
        {
            "count": 1606,
            "name": "她比烟花寂寞",
            "title": "她比烟花寂寞"
        },
        {
            "count": 1273,
            "name": "小说",
            "title": "小说"
        },
        {
            "count": 730,
            "name": "香港",
            "title": "香港"
        },
        {
            "count": 562,
            "name": "爱情",
            "title": "爱情"
        },
        {
            "count": 443,
            "name": "言情",
            "title": "言情"
        },
        {
            "count": 319,
            "name": "师太",
            "title": "师太"
        },
        {
            "count": 218,
            "name": "中国文学",
            "title": "中国文学"
        }
    ],
    "origin_title": "",
    "image": "https://img1.doubanio.com/view/subject/m/public/s1041807.jpg",
    "binding": "平装",
    "translator": [],
    "catalog": "目录",
    "pages": "203",
    "images": {
        "small": "https://img1.doubanio.com/view/subject/s/public/s1041807.jpg",
        "large": "https://img1.doubanio.com/view/subject/l/public/s1041807.jpg",
        "medium": "https://img1.doubanio.com/view/subject/m/public/s1041807.jpg"
    },
    "alt": "https://book.douban.com/subject/1030153/",
    "id": "1030153",
    "publisher": "海天出版社",
    "isbn10": "7806154507",
    "isbn13": "9787806154502",
    "title": "她比烟花寂寞",
    "url": "https://api.douban.com/v2/book/1030153",
    "alt_title": "",
    "author_intro": "",
    "summary": "姚晶这位当红女影星英年去世，身后的遗产竟没有人想要。生前人们迷幻于她的美丽、财富及豪门夫家，然而有谁知道她内心的苦闷与悲凉，正是这外表的灿烂和内心的寂寞组成了她丰富的人生。\n\n漫漫人生，直义何在……",
    "series": {
        "id": "5510",
        "title": "亦舒作品系列"
    },
    "price": "9.80"
}