{
    "rating": {
        "max": 10,
        "numRaters": 11848,
        "average": "7.5",
        "min": 0
    },
    "subtitle": "",
    "author": [
        "余秋雨"
    ],
    "pubdate": "2004-08",
    "tags": [
        {
            "count": 3241,
            "name": "余秋雨",
            "title": "余秋雨"
        },
        {
            "count": 1286,
            "name": "借我一生",
            "title": "借我一生"
        },
        {
            "count": 1199,
            "name": "传记",
            "title": "传记"
        },
        {
            "count": 1021,
            "name": "散文",
            "title": "散文"
        },
        {
            "count": 842,
            "name": "回忆",
            "title": "回忆"
        },
        {
            "count": 645,
            "name": "中国文学",
            "title": "中国文学"
        },
        {
            "count": 478,
            "name": "文学",
            "title": "文学"
        },
        {
            "count": 406,
            "name": "散文随笔",
            "title": "散文随笔"
        }
    ],
    "origin_title": "",
    "image": "https://img9.doubanio.com/view/subject/m/public/s1042736.jpg",
    "binding": "平装",
    "translator": [],
    "catalog": "第一卷\n第一章 长辈的山\n第二章 乡间的事\n第三章 旧屋与旗袍\n第四章 祭侄贴\n第五章 独身的叔叔和姨妈\n第二卷\n第一章 载黑边眼镜的青年\n第二章 叔叔走了\n第三章 一物一物\n第四章 冬天的斯坦尼\n第五章 绛红的泥水\n第六章 关闭的窗户\n第七章 吴石岭\n第八章 半山失踪\n第九章 隐秘的河湾\n第三卷\n第一章 骆驼殿堂\n第二章 有人敲门\n第三章 我能听到\n第四章 湿漉漉的落叶\n第四卷\n第一章 那么走吧\n第二章 从废墟到废墟\n第三章 红缎虎头鞋\n第四章 房主不在屋内\n第五卷\n第一章 墓地和法院\n第二章 那一叠纸条\n第三章 借住何处",
    "pages": "617",
    "images": {
        "small": "https://img9.doubanio.com/view/subject/s/public/s1042736.jpg",
        "large": "https://img9.doubanio.com/view/subject/l/public/s1042736.jpg",
        "medium": "https://img9.doubanio.com/view/subject/m/public/s1042736.jpg"
    },
    "alt": "https://book.douban.com/subject/1049215/",
    "id": "1049215",
    "publisher": "作家出版社",
    "isbn10": "7506330156",
    "isbn13": "9787506330152",
    "title": "借我一生",
    "url": "https://api.douban.com/v2/book/1049215",
    "alt_title": "",
    "author_intro": "余秋雨，一九四六年生，浙江余姚人。在家乡读完小学后到上海读中学和大学，大学毕业后留校任教至今。在海内外出版过史论专著多部，曾被授予“国家级突出贡献专家”、“上海市十大高教精英”等荣誉称号。做过几年学院院长，辞职后潜心写作，在繁多的头衔中比较重视上海市写作学会一职，因为这个学会由全上海各大学的写作教授们组成，专门研究“写作”究竟是怎么回事。",
    "summary": "编辑推荐：余秋雨先生说：　　「我历来不赞成处于创造过程中的艺术家太激动，但写《借我一生》这本书，常常泪流不止。」\n无庸置疑，开创一代散文风尚的余秋雨，早已是当今最有影响力的跨地域华文作家之一。这本新着的创作，更由文化兴叹走向生命洞见。\n余秋雨的父亲在年前去世，家人打开他天天紧锁的私人抽屉发现了大量的文字资料。这些文字资料为什么留存到生命的最后，却又不愿意在生前让后辈看见？由这些疑问出发，",
    "price": "42.00元"
}