{
    "rating": {
        "max": 10,
        "numRaters": 13623,
        "average": "8.4",
        "min": 0
    },
    "subtitle": "",
    "author": [
        "[日] 村上春树"
    ],
    "pubdate": "2002-11",
    "tags": [
        {
            "count": 4409,
            "name": "村上春树",
            "title": "村上春树"
        },
        {
            "count": 1238,
            "name": "小说",
            "title": "小说"
        },
        {
            "count": 1129,
            "name": "日本文学",
            "title": "日本文学"
        },
        {
            "count": 1129,
            "name": "日本",
            "title": "日本"
        },
        {
            "count": 1103,
            "name": "奇鸟行状录",
            "title": "奇鸟行状录"
        },
        {
            "count": 387,
            "name": "村上春樹",
            "title": "村上春樹"
        },
        {
            "count": 327,
            "name": "文学",
            "title": "文学"
        },
        {
            "count": 280,
            "name": "外国文学",
            "title": "外国文学"
        }
    ],
    "origin_title": "",
    "image": "https://img9.doubanio.com/view/subject/m/public/s1152845.jpg",
    "binding": "平装",
    "translator": [
        "林少华"
    ],
    "catalog": "村上春树的小说世界及其艺术魅力（总序）\n第一部 贼喜鹊篇\n1 星期二的拧发条鸟、六根手指与四个乳房\n2 满月与日食、仓房中死去的马们\n3 加纳马耳他的帽子、果汁冰淇淋色调与艾伦・金斯伯格与十字军\n4 高塔与深井、或远离诺门坎\n5 柠檬糖中毒、不能飞的鸟与干涸的井\n6 冈田久美子如何生长、绵谷升如何生长\n7 幸福的洗衣店、加纳克里他的出现\n8 加纳克里他的长话、关于痛苦的考察\n……\n第二部 预言鸟篇\n1 尽可能具体的事情、文学里的食欲\n2 这一章里好消息一个没有\n3 绵谷升的话、下流岛上的下流猴\n4 失却的宠幸、意识娼妇\n5 远方街市的风景、永远的弯月、固定的绳梯\n6 遗产继承、关于水母的研究、近似乖戾感的感觉\n7 关于妊娠的回想与对话、有关痛苦的实验性考察\n8 欲望之根、208房间、破壁而过\n9 井与星、绳梯是怎样消失的\n……\n第三部 捕鸟人篇\n1 笠原May的视点\n2 上吊宅院之谜\n3 冬天里的拧发条鸟\n4 冬眠醒来、另一枚名片、钱的无名性\n5 深夜怪事\n6 买新鞋、返回家中的\n7 细想之下即可知道的地方（笠原May视点之二）\n8 肉豆蔻与肉桂\n……\n村上春树年谱",
    "pages": "682",
    "images": {
        "small": "https://img9.doubanio.com/view/subject/s/public/s1152845.jpg",
        "large": "https://img9.doubanio.com/view/subject/l/public/s1152845.jpg",
        "medium": "https://img9.doubanio.com/view/subject/m/public/s1152845.jpg"
    },
    "alt": "https://book.douban.com/subject/1212080/",
    "id": "1212080",
    "publisher": "上海译文出版社",
    "isbn10": "7532729532",
    "isbn13": "9787532729531",
    "title": "奇鸟行状录",
    "url": "https://api.douban.com/v2/book/1212080",
    "alt_title": "",
    "author_intro": "村上春树（1949- ），日本小说家。曾在早稻田大学文学部戏剧科就读。1979年，他的第一部小说《听风之歌》问世后，即被搬上了银幕。随后，他的优秀作品《1973年的弹子球》、《寻羊冒险记》、《挪威的森林》等相继发表。他的创作不受传统拘束，构思新奇，行文潇洒自在，而又不流于庸俗浅薄。尤其是在刻画人的孤独无奈方面更有特色，他没有把这种情绪写成负的东西，而是通过内心的心智性操作使之升华为一种优雅的格调，一种乐在其中的境界，以此来为读者，尤其是生活在城市里的人们提供了一种生活模式或生命的体验。",
    "summary": "《奇鸟行状录》是村上春树篇幅最长的小说三部曲。\n失业者冈田亨的妻子久美子在其兄长、众议员，黑暗势力代表人物绵谷升的胁迫下失踪了。冈田身边来了许多怪人：女巫师、“意识娼妇”、失手使男友车祸死亡的少女、旧军人等。同时也发生了许多怪事。冈田到一口深井里冥思苦想后，出来在奇怪的母子“肉豆蔻”、“肉桂”的帮助下向绵谷升挑战，在虚幻中将其击伤，久美子又在现实中将其杀死。作品色彩诡异，规模宏大，虚实交叉，被称为当代的“一千零一夜”。",
    "series": {
        "id": "120",
        "title": "村上春树文集（2001版）"
    },
    "price": "30.00元"
}