{
    "rating": {
        "max": 10,
        "numRaters": 3961,
        "average": "7.7",
        "min": 0
    },
    "subtitle": "超越产业竞争，开创全新市场",
    "author": [
        "[韩] W.钱·金",
        "[美] 勒妮·莫博涅"
    ],
    "pubdate": "2005-5",
    "tags": [
        {
            "count": 1645,
            "name": "管理",
            "title": "管理"
        },
        {
            "count": 1521,
            "name": "蓝海战略",
            "title": "蓝海战略"
        },
        {
            "count": 1225,
            "name": "商业",
            "title": "商业"
        },
        {
            "count": 1056,
            "name": "战略",
            "title": "战略"
        },
        {
            "count": 657,
            "name": "营销",
            "title": "营销"
        },
        {
            "count": 564,
            "name": "经济",
            "title": "经济"
        },
        {
            "count": 468,
            "name": "创新",
            "title": "创新"
        },
        {
            "count": 463,
            "name": "市场",
            "title": "市场"
        }
    ],
    "origin_title": "Blue Ocean Strategy",
    "image": "https://img1.doubanio.com/view/subject/m/public/s1513878.jpg",
    "binding": "平装16开",
    "translator": [
        "吉宓"
    ],
    "catalog": "译者序\n前言\n致谢\n第一部分 蓝海战略\n第一章 开创蓝海\n第二章 分析工具和框架\n第二部分 制定蓝海战略\n第三章 重建市场边界\n第四章 注重全局而非数字\n第五章 超越现有需求\n第六章 遵循合理的战略顺序\n第三部分 执行蓝海战略\n第七章 克服关键组织障碍\n第八章 将战略执行建成战略的一部分\n第九章 结论：蓝海战略的可持续性及更新\n附录一 开创蓝海的历史模式概览\n附录二 重建主义的战略观点\n附录三 价值创新的市场动态\n注释\n参考文献\n作者简介",
    "pages": "264",
    "images": {
        "small": "https://img1.doubanio.com/view/subject/s/public/s1513878.jpg",
        "large": "https://img1.doubanio.com/view/subject/l/public/s1513878.jpg",
        "medium": "https://img1.doubanio.com/view/subject/m/public/s1513878.jpg"
    },
    "alt": "https://book.douban.com/subject/1318427/",
    "id": "1318427",
    "publisher": "商务印书馆",
    "isbn10": "7100044529",
    "isbn13": "9787100044523",
    "title": "蓝海战略",
    "url": "https://api.douban.com/v2/book/1318427",
    "alt_title": "Blue Ocean Strategy",
    "author_intro": "W.钱·金是欧洲工商管理学院（INSEAD）波士顿咨询集团布鲁斯·D.亨德森战略和国际管理教席教授。在加入欧洲工商管理学院之前，他曾是密歇根大学商学院的教授。他也是欧洲、美国和亚洲一些跨国公司的董事会成员或顾问。他是达沃斯世界经济论坛的会员和欧盟的顾问成员。\n勒妮·莫博涅是欧洲工商管理学院的杰出学者，战略和管理学教授。她也是世界经济论坛的会员。\n金和莫博涅作为合作伙伴，在《管理学会期刊》、《管理科学》、《组织科学》、《战略管理期刊》、《行政管理学季刊》、《国际商业研究期刊》、《哈佛商业评论》、《斯隆管理评论》等专业期刊上共同发表了为数众多的有关战略和跨国公司管理的文章。他们在《哈佛商业评论》上发表的文章成为全球畅销文章，先后重印了50万份。他们还为《金融时报》、《华尔街日报》、《华尔街日报欧洲版》、《亚洲华尔街日报》、《纽约时报》、《南华早报》等报纸撰写文章。他们曾获得由国际商业学会和埃尔德里奇·海恩斯纪念基金颁发的埃尔德里奇·海恩斯奖，以表彰他们在国际商业领域的最佳原创性论文。金教授和莫博涅教授都是价值创新网络（Value Innovation Network，VIN）的缔造者，这个网络是由价值创新系列感念的实践者组成的全球社团。他们也是设在新加坡的价值创新行动库（Value Innovation Action Tank，VIAT）的董事会成员。",
    "summary": "企业为了寻求持久的、获利性的增长，往往与其对手针锋相对地竞争。它们为竞争优势而战，为市场份额而战，为实现差异化而战。\n然而在目前过度拥挤的产业市场中，硬碰硬的竞争只能令企业陷入血腥的“红海”，即竞争激烈的已知市场空间中，并与对手争抢日益缩减的利润额。在这本书中，作者对你所熟知的一切战略成功的定律提出挑战。他们认为，流连于红海的竞争之中，将越来越难以创造未来的获利性增长。\n作者基于对跨度达100多年、涉及30多个产业的150个战略行动的研究，提出：要赢得明天，企业不能靠与对手竞争，而是要开创“蓝海”，即蕴含庞大需求的新市场空间，以走上增长之路。这种被称为“价值创新”的战略行动能够为企业和买方都创造价值的飞跃，使企业彻底甩脱竞争对手，并将新的需求释放出来。\n《蓝海战略》为企业甩脱竞争提供了一套系统性的方法。在这本颠覆传统战略思维的著作中，作者展示了一套经过实践证明的分析框架和工具，供企业成功地开创和夺取蓝海。通过对各种产业中为数众多的战略行动的分析，作者还提出了成功制定和执行蓝海战略的六项原则。这些原则告诉企业，该如何重建市场边界、注重全局、超越现有需求、遵循合理的战略顺序、克服组织障碍并把战略的执行建成战略的一部分。",
    "price": "38.00元"
}