{
    "rating": {
        "max": 10,
        "numRaters": 2493,
        "average": "8.4",
        "min": 0
    },
    "subtitle": "（全四册）",
    "author": [
        "金庸"
    ],
    "pubdate": "1976",
    "tags": [
        {
            "count": 571,
            "name": "金庸",
            "title": "金庸"
        },
        {
            "count": 347,
            "name": "武侠",
            "title": "武侠"
        },
        {
            "count": 178,
            "name": "小说",
            "title": "小说"
        },
        {
            "count": 141,
            "name": "武侠小说",
            "title": "武侠小说"
        },
        {
            "count": 122,
            "name": "倚天屠龙记",
            "title": "倚天屠龙记"
        },
        {
            "count": 71,
            "name": "香港",
            "title": "香港"
        },
        {
            "count": 66,
            "name": "武俠",
            "title": "武俠"
        },
        {
            "count": 60,
            "name": "中国文学",
            "title": "中国文学"
        }
    ],
    "origin_title": "",
    "image": "https://img1.doubanio.com/view/subject/m/public/s1367119.jpg",
    "binding": "",
    "translator": [],
    "catalog": "",
    "pages": "1662",
    "images": {
        "small": "https://img1.doubanio.com/view/subject/s/public/s1367119.jpg",
        "large": "https://img1.doubanio.com/view/subject/l/public/s1367119.jpg",
        "medium": "https://img1.doubanio.com/view/subject/m/public/s1367119.jpg"
    },
    "alt": "https://book.douban.com/subject/1337292/",
    "id": "1337292",
    "publisher": "明河社",
    "isbn10": "9627461199",
    "isbn13": "9789627461197",
    "title": "倚天屠龍記",
    "url": "https://api.douban.com/v2/book/1337292",
    "alt_title": "",
    "author_intro": "",
    "summary": "明河社版《倚天屠龍記》，一九七六年十二月初版（1-3冊，第4冊爲“一九七七年三月初版”），有一九七八年八月再版、一九八一年版、1998年第21版",
    "series": {
        "id": "310",
        "title": "金庸作品集（明河社）"
    },
    "price": "HK$160"
}