{
    "rating": {
        "max": 10,
        "numRaters": 14338,
        "average": "8.0",
        "min": 0
    },
    "subtitle": "",
    "author": [
        "九把刀"
    ],
    "pubdate": "2006-1",
    "tags": [
        {
            "count": 3373,
            "name": "九把刀",
            "title": "九把刀"
        },
        {
            "count": 1577,
            "name": "小说",
            "title": "小说"
        },
        {
            "count": 1486,
            "name": "惊悚",
            "title": "惊悚"
        },
        {
            "count": 1332,
            "name": "阴暗的人性",
            "title": "阴暗的人性"
        },
        {
            "count": 925,
            "name": "偷窥",
            "title": "偷窥"
        },
        {
            "count": 907,
            "name": "台湾",
            "title": "台湾"
        },
        {
            "count": 814,
            "name": "楼下的房客",
            "title": "楼下的房客"
        },
        {
            "count": 793,
            "name": "恐怖",
            "title": "恐怖"
        }
    ],
    "origin_title": "",
    "image": "https://img1.doubanio.com/view/subject/m/public/s1507168.jpg",
    "binding": "平装",
    "translator": [],
    "catalog": "",
    "pages": "291",
    "images": {
        "small": "https://img1.doubanio.com/view/subject/s/public/s1507168.jpg",
        "large": "https://img1.doubanio.com/view/subject/l/public/s1507168.jpg",
        "medium": "https://img1.doubanio.com/view/subject/m/public/s1507168.jpg"
    },
    "alt": "https://book.douban.com/subject/1485495/",
    "id": "1485495",
    "publisher": "花山文艺出版社",
    "isbn10": "7806736824",
    "isbn13": "9787806736821",
    "title": "楼下的房客",
    "url": "https://api.douban.com/v2/book/1485495",
    "alt_title": "",
    "author_intro": "九把刀，本名柯景腾，东海大学研究生，网坛文学高手。99 年以中篇小说《恐惧炸弹》在网络上一炮而红。部分作品在台湾新生报等媒体连载，读者反应热烈，目前网络文学最大站猫园中长篇小说版最具人气的作家！被誉为“网络文学经典制造机”。九把刀在写作上自创一种黑色神经喜剧的风格，用词辛辣，奇想联翩，好笑且诱人深省，别有一番神奇寓意。",
    "summary": "小说是一部悬疑而又诡异的出租屋的故事。详细描述了每个人的外型、特征、癖好，运用一个思想怪异的房东把他们串联成一个个恐怖的故事。\n一个继承出租公寓的无业游民，在东海大学附近贴起招租布告，他不要家世清白的乖乖牌学生、不要收支稳定的上班族、不要勤俭质朴的小家庭，他只要“正常人”，像任何符合正常定义，有混乱潜质的正常人，能满足他偷窥正常面具下的黑暗面的正常人。因此，有家暴前科的体育老师老张、黏在网上的大学生伯彦、失婚的王先生和纯洁像天使的王小妹、神秘作家颖如、同性人令狐和郭力、上班尤物陈小姐一起搬到了出租公寓。八个房客还有一个变态房东，六个房间外加一堆秘密。人性潜在的可能性，使我们无法预测每个房间到底还有多少隐私。",
    "price": "19.80元"
}