{
    "rating": {
        "max": 10,
        "numRaters": 2486,
        "average": "7.8",
        "min": 0
    },
    "subtitle": "回家真好之二",
    "author": [
        "欧阳应霁"
    ],
    "pubdate": "2005-12",
    "tags": [
        {
            "count": 1313,
            "name": "欧阳应霁",
            "title": "欧阳应霁"
        },
        {
            "count": 670,
            "name": "设计",
            "title": "设计"
        },
        {
            "count": 543,
            "name": "生活",
            "title": "生活"
        },
        {
            "count": 523,
            "name": "梦·想家",
            "title": "梦·想家"
        },
        {
            "count": 383,
            "name": "家居",
            "title": "家居"
        },
        {
            "count": 203,
            "name": "随笔",
            "title": "随笔"
        },
        {
            "count": 171,
            "name": "三联",
            "title": "三联"
        },
        {
            "count": 153,
            "name": "香港",
            "title": "香港"
        }
    ],
    "origin_title": "",
    "image": "https://img1.doubanio.com/view/subject/m/public/s1566378.jpg",
    "binding": "平装16开",
    "translator": [],
    "catalog": "",
    "pages": "155",
    "images": {
        "small": "https://img1.doubanio.com/view/subject/s/public/s1566378.jpg",
        "large": "https://img1.doubanio.com/view/subject/l/public/s1566378.jpg",
        "medium": "https://img1.doubanio.com/view/subject/m/public/s1566378.jpg"
    },
    "alt": "https://book.douban.com/subject/1449661/",
    "id": "1449661",
    "publisher": "生活·读书·新知三联书店",
    "isbn10": "7108023407",
    "isbn13": "9787108023407",
    "title": "梦·想家",
    "url": "https://api.douban.com/v2/book/1449661",
    "alt_title": "",
    "author_intro": "当被问到为什么要选择创作的路，他回答说，因为有趣。当被问到是什么叫他一直兴高采烈地走下去，他回答说：就是好玩。 他一路放肆贪玩，却又专一迷恋文字和图像之问的微妙暧昧，不小心也很自然地跨界破例——相信旅行，钟情漫画，关注设计，沉迷杂志，狂恋占乐，爱恨美食……\n自香港理工大学设计系获取荣誉学土及哲学硕士以来，长期对现代家居生活及建筑设计潮流观察研究，大量撰写相关评论推介文章，发表于大陆、港、台报章杂志。出版有生活写作系列《一日一日》、《寻常放荡》、《两个人住》、《回家真好》、《设计私生活》及《半饱》。文字写作以外同时热衷漫画创作，出版有《我的天》、《爱到死》、《小明》、《三七廿一》、《我的天使》等漫画系列及专集。 停不了——矢志做个贪心的、快活的、认真的跨媒体导游。",
    "summary": "《梦，想家》采录大陆、港、台十八位创作人的家居风景，展示两岸三地华人的精彩生活与艺术世界。",
    "series": {
        "id": "4535",
        "title": "Home书系"
    },
    "price": "28.00元"
}