{
    "rating": {
        "max": 10,
        "numRaters": 15082,
        "average": "9.0",
        "min": 0
    },
    "subtitle": "",
    "author": [
        "王小波"
    ],
    "pubdate": "2006-4",
    "tags": [
        {
            "count": 5271,
            "name": "王小波",
            "title": "王小波"
        },
        {
            "count": 2710,
            "name": "杂文",
            "title": "杂文"
        },
        {
            "count": 1710,
            "name": "沉默的大多数",
            "title": "沉默的大多数"
        },
        {
            "count": 1197,
            "name": "思想",
            "title": "思想"
        },
        {
            "count": 1129,
            "name": "随笔",
            "title": "随笔"
        },
        {
            "count": 897,
            "name": "中国文学",
            "title": "中国文学"
        },
        {
            "count": 560,
            "name": "中国",
            "title": "中国"
        },
        {
            "count": 549,
            "name": "文学",
            "title": "文学"
        }
    ],
    "origin_title": "",
    "image": "https://img9.doubanio.com/view/subject/m/public/s1727466.jpg",
    "binding": "平装",
    "translator": [],
    "catalog": "沉默的大多数\n思维的乐趣\n中国知识分子与中古遗风\n知识分子的不幸\n花剌子模信使问题\n积极的结论\n跳出手掌心\n道德堕落与知识分子\n论战与道德\n道德保护主义及其他\n我看文化热\n文化之争\n“行货感”与文化相对主义\n极端体验\n洋鬼子与辜鸿铭\n我看国学\n智慧与国学\n理想国与哲人王\n救世情结与白日梦\n百姓·洋人·官\n警惕狭隘民族主义的蛊惑宣传\n对中国文化的布罗代尔式考证\n人性的逆转\n弗洛伊德和受虐狂\n有关天圆地方\n优越感种种\n东西方快乐观区别之我见\n肚子里的战争\n一只特立独行的猪\n椰子树与平等\n思想和害臊\n体验生活\n皇帝做习题\n拒绝恭维\n关于崇高\n谦卑学习班\n荷兰牧场与父老乡亲\n京片子与民族自信心\n高考经历\n盛装舞步\n有关“错误的故事”\n迷信与邪门书\n科学与邪道\n科学的美好\n生命科学与骗术\n我是哪一种女权主义者\n我怎样做青年的思想工作\n有关“伟大一族”\n有关“给点气氛”\n我看老三届\n苏东坡与东坡肉\n摆脱童稚状态\n与同性恋有关的伦理问题\n《他们的世界》序\n《他们的世界》跋\n诚实与浮嚣\n不新的《万历十五年》\n《代价论》、乌托邦与圣贤\n《我为什么要写作》—《时代三部曲》总序\n我的师承——《青铜时代序》\n我的精神家园\n我对小说的看法\n小说的艺术\n《黄金时代》后记\n《红拂夜奔》序\n盖茨的紧身衣\n关于文体\n关于格调\n关于幽闭型小说\n文明与反讽\n关于“媚雅”\n长虫·草帽·细高挑\n卡拉OK与驴鸣镇\n从Internet说起\n“奸近杀”\n电影·韭菜·旧报纸\n商业片与艺术片\n我对国产片的看法\n旧片重温\n为什么老片新拍\n欣赏经典\n都市言情剧里的爱情\n《祝你平安》与音乐电视\n承认的勇气\n明星与癫狂\n另一种文化\n艺术与关怀弱势群体\n在美国左派家作客\n门前空地\n卖唱的人们\n打工经历\n自然景观和人文景观\n文化的园地\n环境问题\n工作与人生\n王朔的作品\n后记\n浪漫骑士",
    "pages": "243",
    "images": {
        "small": "https://img9.doubanio.com/view/subject/s/public/s1727466.jpg",
        "large": "https://img9.doubanio.com/view/subject/l/public/s1727466.jpg",
        "medium": "https://img9.doubanio.com/view/subject/m/public/s1727466.jpg"
    },
    "alt": "https://book.douban.com/subject/1776683/",
    "id": "1776683",
    "publisher": "北方文艺出版社",
    "isbn10": "7531719185",
    "isbn13": "9787531719182",
    "title": "沉默的大多数",
    "url": "https://api.douban.com/v2/book/1776683",
    "alt_title": "",
    "author_intro": "王小波，1997年，四十五岁，4月11日，因心脏病突发辞世。4月26日，王小波遗体告别仪式在北京八宝山公墓举行。5月，杂文集《我的精神家园》由文化艺术出版社出版。10月《觉默的大多数——王小波杂文随笔全编》由中国青年出版社出版。10月，《沉默的大多数》由香港明镜出版社出版。",
    "summary": "我对自己的要求很低：我活在世上，无非想要明白些道理，遇见些有趣的事。倘能如我所愿，我的一生就算成功。为此也要去论是非，否则道理不给你明白，有趣的事也不让你遇到。我开始得太晚了，很可能做不成什么，但我总得申明我的态度，所以就有了这本书——为我自己，也代表沉默的大多数。\n——王小波",
    "series": {
        "id": "1633",
        "title": "王小波作品选集"
    },
    "price": "18.80元"
}