{
    "rating": {
        "max": 10,
        "numRaters": 112957,
        "average": "8.8",
        "min": 0
    },
    "subtitle": "",
    "author": [
        "王小波",
        "李银河"
    ],
    "pubdate": "2008-5",
    "tags": [
        {
            "count": 23947,
            "name": "王小波",
            "title": "王小波"
        },
        {
            "count": 12561,
            "name": "爱你就像爱生命",
            "title": "爱你就像爱生命"
        },
        {
            "count": 11382,
            "name": "爱情",
            "title": "爱情"
        },
        {
            "count": 10330,
            "name": "李银河",
            "title": "李银河"
        },
        {
            "count": 9298,
            "name": "情书",
            "title": "情书"
        },
        {
            "count": 8660,
            "name": "书信集",
            "title": "书信集"
        },
        {
            "count": 4467,
            "name": "中国文学",
            "title": "中国文学"
        },
        {
            "count": 4032,
            "name": "散文",
            "title": "散文"
        }
    ],
    "origin_title": "",
    "image": "https://img2.doubanio.com/view/subject/m/public/s4661043.jpg",
    "binding": "平装",
    "translator": [],
    "catalog": "一、序\n二、诗人之爱，王小波情书选\n最初的呼唤\n爱你就像爱生命\n痛悔\n真正的婚姻全是在天上缔结的\n请你不要吃我，我给你唱一支好听的歌\n孤独的灵魂多么寂寞啊\n我是一只骆驼\n我对好多人怀有最深的感情，尤其是对你\n吾友李银河\n我现在想认真了\n假如你愿意，你就恋爱吧\n美好的时光\n去上大学\n人为什么活着\n你和我是很不同的人\n孤独是丑的\n我要你，和我有宿缘的人\n没有你的生活\n我就要放个震动北京城的大炮仗\n目空一切的那种爱\n爱情真美\n我厌恶模式化的生活\n我在家里爱你爱得要命\n我好像害了牙痛\n夏天好吗？\n他们的教条比斑马还多\n假如我像但丁或彼得拉那样\n口齿不灵\n哑巴爱\n写在五线谱上的信\n三、浪漫骑士·行吟诗人·自由思想者\n四、我们曾经拥有\n五、《绿毛水怪》和我们的爱情\n六、绿毛水怪\n七、我在荒岛上迎接黎明",
    "pages": "222",
    "images": {
        "small": "https://img2.doubanio.com/view/subject/s/public/s4661043.jpg",
        "large": "https://img2.doubanio.com/view/subject/l/public/s4661043.jpg",
        "medium": "https://img2.doubanio.com/view/subject/m/public/s4661043.jpg"
    },
    "alt": "https://book.douban.com/subject/3071717/",
    "id": "3071717",
    "publisher": "上海锦绣文章出版社",
    "isbn10": "7806859985",
    "isbn13": "9787806859988",
    "title": "爱你就像爱生命",
    "url": "https://api.douban.com/v2/book/3071717",
    "alt_title": "",
    "author_intro": "王小波，1952年出生。一个特立独行的作家。他的作品被誉为“中国当代文坛最美的收获”。自1997年4月11日去世后，他的作品被人们广泛阅读、关注、讨论，并引发了“王小波热”的文化现象。\n主要作品有《黄金时代》、《白银时代》、《青铜时代》、《我的精神家园》、《沉默的大多数》、《黑铁时代》、《地久天长》：纪念、评论集有  《浪漫骑士》、《不再沉默》、《王小波画传》。\n李银河，1952年生于北京，王小波的遗孀。中国社会科学院社会学研究所研究员、博士生导师，美国匹兹堡大学社会博士、北京大学社会学博士后。\n主要著作有《同性恋亚文化》、《中国人的性爱与婚姻》、《中国女性的性与爱》等。",
    "summary": "王小波书信均选自朝华出版社2004年4月第一版《爱你就像爱生命》，此书系王小波生前从未发表过的与李银河的“两地书”，也是迄今他们夫妇最完整和独立的一本书信集。",
    "series": {
        "id": "3439",
        "title": "王小波作品全集（磨铁2008版）"
    },
    "price": "18.00元"
}